CVUtils/CVUtils.py
CVUtils/__init__.py
CVUtils/test.py
CVUtils/files/WordAndNum.txt
CVUtils/files/province.txt
SpiderUtils/SpiderUtils.py
SpiderUtils/SpiderUtils_冲突文件_ming_20230916103617.py
SpiderUtils/__init__.py
SpiderUtils/files/stopwords.txt
MingLogUtils-2.0.4.dist-info/LICENSE
MingLogUtils-2.0.4.dist-info/METADATA
MingLogUtils-2.0.4.dist-info/WHEEL
MingLogUtils-2.0.4.dist-info/top_level.txt
MingLogUtils-2.0.4.dist-info/RECORD
