Metadata-Version: 2.1
Name: MingLogUtils
Version: 2.0.4
Summary: 自定义相关工具库
Home-page: http://minglog.hzbmmc.com
Author: MingLog
Author-email: 736704198@qq.com
License: MIT
Classifier: Development Status :: 3 - Alpha
Classifier: Intended Audience :: Developers
Classifier: License :: OSI Approved :: MIT License
Classifier: Programming Language :: Python
Classifier: Programming Language :: Python :: 3
Classifier: Programming Language :: Python :: 3.6
Classifier: Programming Language :: Python :: 3.7
Classifier: Programming Language :: Python :: 3.8
Classifier: Programming Language :: Python :: 3.9
License-File: LICENSE
Requires-Dist: numpy
Requires-Dist: matplotlib
Requires-Dist: pillow
Requires-Dist: opencv-python
Requires-Dist: aiofiles
Requires-Dist: scipy
Requires-Dist: pandas
Requires-Dist: requests
